{
  "name": "MeasurementActivity.view_edit",
  "title": "Measurement",
  "type": "view_edit",
  "templates": [
    {
      "cells": [
        [
          {
            "width": "4",
            "height": "1",
            "template": {
              "cells": [
                [
                  {
                    "width": "3",
                    "height": "1"
                  },
                  {
                    "width": "3",
                    "height": "1"
                  },
                  {
                    "width": "3",
                    "height": "1"
                  },
                  {
                    "width": "3",
                    "height": "1"
                  }
                ],
                [
                  {
                    "width": "6",
                    "height": "1"
                  },
                  {
                    "width": "6",
                    "height": "1"
                  }
                ]
              ],
              "type": "table"
            },
            "attributeName": "tarsus_length"
          },
          {
            "width": "4",
            "height": "1",
            "template": {
              "cells": [
                [
                  {
                    "width": "3",
                    "height": "1"
                  },
                  {
                    "width": "3",
                    "height": "1"
                  },
                  {
                    "width": "3",
                    "height": "1"
                  },
                  {
                    "width": "3",
                    "height": "1"
                  }
                ],
                [
                  {
                    "width": "6",
                    "height": "1"
                  },
                  {
                    "width": "6",
                    "height": "1"
                  }
                ]
              ],
              "type": "table"
            },
            "attributeName": "tarsus_width"
          },
          {
            "width": "4",
            "height": "1",
            "template": {
              "cells": [
                [
                  {
                    "width": "3",
                    "height": "1"
                  },
                  {
                    "width": "3",
                    "height": "1"
                  },
                  {
                    "width": "3",
                    "height": "1"
                  },
                  {
                    "width": "3",
                    "height": "1"
                  }
                ],
                [
                  {
                    "width": "6",
                    "height": "1"
                  },
                  {
                    "width": "6",
                    "height": "1"
                  }
                ]
              ],
              "type": "table"
            },
            "attributeName": "tarsus_depth"
          }
        ],
        [
          {
            "width": "4",
            "height": "1",
            "template": {
              "cells": [
                [
                  {
                    "width": "3",
                    "height": "1"
                  },
                  {
                    "width": "3",
                    "height": "1"
                  },
                  {
                    "width": "3",
                    "height": "1"
                  },
                  {
                    "width": "3",
                    "height": "1"
                  }
                ],
                [
                  {
                    "width": "6",
                    "height": "1"
                  },
                  {
                    "width": "6",
                    "height": "1"
                  }
                ]
              ],
              "type": "table"
            },
            "attributeName": "bill_length"
          }
        ]
      ],
      "metaEntityName": "MeasurementActivity",
      "type": "form"
    }
  ]
}